Metadata-Version: 2.4
Name: pydaikin_custom
Version: 2.16.0
Summary: Python Daikin HVAC appliances interface
Author-email: Christopher Carruthers <christopher971991@gmail.com>, Fredrik Erlandsson <fredrik.e@gmail.com>, Yari Adan <mustang@yadan.org>
Maintainer-email: Christopher Carruthers <christopher971991@gmail.com>
Project-URL: Homepage, https://github.com/Chris971991/pydaikin-2.8.0
Project-URL: Repository, https://github.com/Chris971991/pydaikin-2.8.0.git
Project-URL: Issues, https://github.com/Chris971991/pydaikin-2.8.0/issues
Classifier: Programming Language :: Python :: 3
Classifier: Operating System :: OS Independent
Classifier: Topic :: Software Development :: Libraries :: Application Frameworks
Classifier: Topic :: Home Automation
Requires-Python: >=3.11
Requires-Dist: netifaces
Requires-Dist: aiohttp
Requires-Dist: urllib3
Requires-Dist: tenacity
